mewbot/core/__init__.py
mewbot/core/py.typed
mewbot_core-0.0.3.dist-info/LICENSE.md
mewbot_core-0.0.3.dist-info/METADATA
mewbot_core-0.0.3.dist-info/WHEEL
mewbot_core-0.0.3.dist-info/top_level.txt
mewbot_core-0.0.3.dist-info/RECORD
